COPYING
MANIFEST.in
README.rst
setup.py
conz/__init__.py
conz/ansi_colors.py
conz/console.py
conz/progress.py
conz/utils.py
conz.egg-info/PKG-INFO
conz.egg-info/SOURCES.txt
conz.egg-info/dependency_links.txt
conz.egg-info/top_level.txt