Metadata-Version: 1.1
Name: conz
Version: 0.4
Summary: Library for writing command line programs
Home-page: https://github.com/Outernet-Project/conz
Author: Outernet Inc
Author-email: apps@outernet.is
License: GPLv3
Keywords: console,terminal,signals,output,command line,colorizing
Platform: UNKNOWN
Classifier: Development Status :: 4 - Beta
Classifier: Topic :: Software Development :: Libraries :: Application Frameworks
Classifier: License :: OSI Approved :: GNU General Public License v3 or later (GPLv3+)
Classifier: Programming Language :: Python :: 3.4
Classifier: Programming Language :: Python :: 2.7
